unbelievaboat/Client.py
unbelievaboat/RequestHandler.py
unbelievaboat/__init__.py
unbelievaboat/errors/APIError.py
unbelievaboat/errors/HTTPError.py
unbelievaboat/errors/__init__.py
unbelievaboat/structures/Embed.py
unbelievaboat/structures/Guild.py
unbelievaboat/structures/Leaderboard.py
unbelievaboat/structures/Message.py
unbelievaboat/structures/Permission.py
unbelievaboat/structures/Store.py
unbelievaboat/structures/UserBalance.py
unbelievaboat/structures/UserInventory.py
unbelievaboat/structures/__init__.py
unbelievaboat/structures/items/BaseItem.py
unbelievaboat/structures/items/InventoryItem.py
unbelievaboat/structures/items/StoreItem.py
unbelievaboat/structures/items/StoreItemAction.py
unbelievaboat/structures/items/StoreItemRequirement.py
unbelievaboat/structures/items/__init__.py
unbelievaboat/utils/__init__.py
unbelievaboat/utils/types.py
unbelievaboat-2.2.0.dist-info/LICENSE
unbelievaboat-2.2.0.dist-info/METADATA
unbelievaboat-2.2.0.dist-info/WHEEL
unbelievaboat-2.2.0.dist-info/top_level.txt
unbelievaboat-2.2.0.dist-info/RECORD
