Metadata-Version: 2.1
Name: unbelievaboat
Version: 2.2.0
Summary: Wrapper for UnbelievaBoat API.
Home-page: https://github.com/yoggys/unbelievaboat
Author: yoggys
Author-email: yoggies@yoggies.dev
Keywords: python,unb,unbelievaboat,api,wrapper,async,asyncio
Classifier: Development Status :: 5 - Production/Stable
Classifier: Intended Audience :: Developers
Classifier: License :: OSI Approved :: MIT License
Classifier: Programming Language :: Python :: 3
Classifier: Programming Language :: Python :: 3.8
Classifier: Programming Language :: Python :: 3.9
Classifier: Programming Language :: Python :: 3.10
Classifier: Programming Language :: Python :: 3.11
Classifier: Programming Language :: Python :: 3.12
Classifier: Programming Language :: Python :: 3.13
Classifier: Topic :: Internet
Classifier: Topic :: Software Development :: Libraries
Classifier: Topic :: Software Development :: Libraries :: Python Modules
Classifier: Topic :: Utilities
Classifier: Typing :: Typed
License-File: LICENSE
Requires-Dist: aiohttp<3.13.0,>=3.9.2
Requires-Dist: typing_extensions<4.15.0,>=4.12.2
